Workbook

Sheet 条件
A1: 借入額 | B1: 3000000 | C1: ローン年数 | D1: 10
A2: 年利 | B2: 0.049 | D2: =12*D1 -> 120
A3: 返済回数（月） | B3: =D2 -> 120
A4: 月利 | B4: =B2/12 -> 0.0040833333
A5: 毎月返済額 | B5: =-PMT(B4,B3,B1) -> 31673.219

Sheet 返済表
A1: 回数 | B1: 返済額 | C1: 利息 | D1: 元金 | E1: 残高 | F1: 累計支払額
A2: 1 | B2: ='条件'!$B$5 -> 31673.219 | C2: ='条件'!$B$1*'条件'!$B$4 -> 12250 | D2: =B2-C2 -> 19423.219 | E2: ='条件'!$B$1-D2 -> 2980576.8 | F2: =B2 -> 31673.219
A3: =A2+1 -> 2 | B3: ='条件'!$B$5 -> 31673.219 | C3: =E2*'条件'!$B$4 -> 12170.689 | D3: =B3-C3 -> 19502.53 | E3: =E2-D3 -> 2961074.3 | F3: =F2 + B3 -> 63346.437
A4: =A3+1 -> 3 | B4: ='条件'!$B$5 -> 31673.219 | C4: =E3*'条件'!$B$4 -> 12091.053 | D4: =B4-C4 -> 19582.165 | E4: =E3-D4 -> 2941492.1 | F4: =F3 + B4 -> 95019.656
A5: =A4+1 -> 4 | B5: ='条件'!$B$5 -> 31673.219 | C5: =E4*'条件'!$B$4 -> 12011.093 | D5: =B5-C5 -> 19662.126 | E5: =E4-D5 -> 2921830 | F5: =F4 + B5 -> 126692.87
A6: =A5+1 -> 5 | B6: ='条件'!$B$5 -> 31673.219 | C6: =E5*'条件'!$B$4 -> 11930.806 | D6: =B6-C6 -> 19742.413 | E6: =E5-D6 -> 2902087.5 | F6: =F5 + B6 -> 158366.09
A7: =A6+1 -> 6 | B7: ='条件'!$B$5 -> 31673.219 | C7: =E6*'条件'!$B$4 -> 11850.191 | D7: =B7-C7 -> 19823.028 | E7: =E6-D7 -> 2882264.5 | F7: =F6 + B7 -> 190039.31
A8: =A7+1 -> 7 | B8: ='条件'!$B$5 -> 31673.219 | C8: =E7*'条件'!$B$4 -> 11769.247 | D8: =B8-C8 -> 19903.972 | E8: =E7-D8 -> 2862360.5 | F8: =F7 + B8 -> 221712.53
A9: =A8+1 -> 8 | B9: ='条件'!$B$5 -> 31673.219 | C9: =E8*'条件'!$B$4 -> 11687.972 | D9: =B9-C9 -> 19985.246 | E9: =E8-D9 -> 2842375.3 | F9: =F8 + B9 -> 253385.75
A10: =A9+1 -> 9 | B10: ='条件'!$B$5 -> 31673.219 | C10: =E9*'条件'!$B$4 -> 11606.366 | D10: =B10-C10 -> 20066.853 | E10: =E9-D10 -> 2822308.4 | F10: =F9 + B10 -> 285058.97
A11: =A10+1 -> 10 | B11: ='条件'!$B$5 -> 31673.219 | C11: =E10*'条件'!$B$4 -> 11524.426 | D11: =B11-C11 -> 20148.792 | E11: =E10-D11 -> 2802159.7 | F11: =F10 + B11 -> 316732.19
A12: =A11+1 -> 11 | B12: ='条件'!$B$5 -> 31673.219 | C12: =E11*'条件'!$B$4 -> 11442.152 | D12: =B12-C12 -> 20231.067 | E12: =E11-D12 -> 2781928.6 | F12: =F11 + B12 -> 348405.41
A13: =A12+1 -> 12 | B13: ='条件'!$B$5 -> 31673.219 | C13: =E12*'条件'!$B$4 -> 11359.542 | D13: =B13-C13 -> 20313.677 | E13: =E12-D13 -> 2761614.9 | F13: =F12 + B13 -> 380078.62
A14: =A13+1 -> 13 | B14: ='条件'!$B$5 -> 31673.219 | C14: =E13*'条件'!$B$4 -> 11276.594 | D14: =B14-C14 -> 20396.624 | E14: =E13-D14 -> 2741218.3 | F14: =F13 + B14 -> 411751.84
... A121: =A120+1 -> 120 | B121: ='条件'!$B$5 -> 31673.219 | C121: =E120*'条件'!$B$4 -> 128.80635 | D121: =B121-C121 -> 31544.412 | E121: =E120-D121 -> 9.7777956e-08 | F121: =F120 + B121 -> 3800786.2

Sheet 一括返済
B1: 下取り | C1: 1000000
B2: 一括返済月 | C2: 1
B3: 一括返済時残高 | C3: ='返済表'!E2 -> 2980576.8 | D3: ←一括返済月からプラス1の値をEのあとに入れる
B4: 手数料 | C4: 0.7
B5: 通常完済時総支払額 | C5: ='条件'!B5*'条件'!B3 -> 3800786.2
A6: =C2 -> 1 | B6: 回までの支払額 | C6: ='条件'!B5*C2 -> 31673.219
A7: =C2/12 -> 0.083333333 | B7: 年目完済時総支払額 | C7: =C6+C3 -> 3012250
B8: 戻り利息(払わなかった利息) | C8: =C5-C7 -> 788536.24
B9: 手数料込み戻り利息 | C9: =C8*C4 -> 551975.37
B11: 残債と下取りの差 | C11: =C5-C6-C9-C1 -> 2217137.7
